MANIFEST.in
README.rst
setup.py
smartdata.egg-info/PKG-INFO
smartdata.egg-info/SOURCES.txt
smartdata.egg-info/dependency_links.txt
smartdata.egg-info/not-zip-safe
smartdata.egg-info/requires.txt
smartdata.egg-info/top_level.txt
smartui/__init__.py
smartui/static/admin/css/autocomplete.css
smartui/static/admin/css/base.css
smartui/static/admin/css/changelists.css
smartui/static/admin/css/dashboard.css
smartui/static/admin/css/fonts.css
smartui/static/admin/css/forms.css
smartui/static/admin/css/login.css
smartui/static/admin/css/responsive.css
smartui/static/admin/css/responsive_rtl.css
smartui/static/admin/css/rtl.css
smartui/static/admin/css/ui.css
smartui/static/admin/css/widgets.css
smartui/static/admin/css/vendor/select2/LICENSE-SELECT2.md
smartui/static/admin/css/vendor/select2/select2.css
smartui/static/admin/css/vendor/select2/select2.min.css
smartui/static/admin/fonts/LICENSE.txt
smartui/static/admin/fonts/README.txt
smartui/static/admin/fonts/Roboto-Bold-webfont.woff
smartui/static/admin/fonts/Roboto-Light-webfont.woff
smartui/static/admin/fonts/Roboto-Regular-webfont.woff
smartui/static/admin/img/LICENSE
smartui/static/admin/img/README.txt
smartui/static/admin/img/calendar-icons.svg
smartui/static/admin/img/favicon.ico
smartui/static/admin/img/icon-addlink.svg
smartui/static/admin/img/icon-alert.svg
smartui/static/admin/img/icon-calendar.svg
smartui/static/admin/img/icon-changelink.svg
smartui/static/admin/img/icon-clock.svg
smartui/static/admin/img/icon-deletelink.svg
smartui/static/admin/img/icon-no.svg
smartui/static/admin/img/icon-unknown-alt.svg
smartui/static/admin/img/icon-unknown.svg
smartui/static/admin/img/icon-viewlink.svg
smartui/static/admin/img/icon-yes.svg
smartui/static/admin/img/inline-delete.svg
smartui/static/admin/img/search.svg
smartui/static/admin/img/selector-icons.svg
smartui/static/admin/img/sorting-icons.svg
smartui/static/admin/img/tooltag-add.svg
smartui/static/admin/img/tooltag-arrowright.svg
smartui/static/admin/img/gis/move_vertex_off.svg
smartui/static/admin/img/gis/move_vertex_on.svg
smartui/static/admin/js/SelectBox.js
smartui/static/admin/js/SelectFilter2.js
smartui/static/admin/js/actions.js
